Workbook

Sheet 报关单
A1: 中华人民共和国海关出口货物报关单
A2: 预录入编号： | L2: 申报口岸 : | T2: 海关编号 :
A3: 境内发货人 | I3: 出境关别 ( ) | N3: 出口日期： | V3: 申报日期： | Z3: 备案号
A4: 91411000MA3X6E9D79 许昌易尚电子商务有限公司 | N4: =V4+3 -> 46163 | V4: 46160
A5: 境外收货人 AEO： Amazon.com Services, Inc. | I5: 运输方式 ( 水路运输 ) | N5: 运输工具名称及航次号 | V5: 提运单号
A6: 生产销售单位 91411000MA3X6E9D79 许昌易尚电子商务有限公司 | I6: 监管方式 ( ) 一般贸易 | N6: 征免性质 ( ) 一般征税 | V6: 许可证号
A7: 合同协议号： | I7: 贸易国(地区): | N7: 运抵国(地区)： | V7: 指运港： | Z7: 离境口岸 ( )跨境的才需要申报
A8: EF-C26037-AVP1 | I8: 美国 | N8: =I8 -> 美国 | V8: =I8 -> 美国
A9: 包装种类： | I9: 件数 | L9: 毛重（千克） | N9: 净重（千克） | T9: 成交方式 ( ) | V9: 运费 | Y9: 保费 | AA9: 杂费
A10: 纸箱 | I10: 61 | L10: =SUM(AC15:AC16) -> 997.35 | N10: =SUM(AD15:AD16) -> 866.81 | T10: FOB
A11: 随附单证及编号 境外收货人完整 ：
A12: 标记唛码及备注： 备注： 报关联系电话：
A13: 特殊关系确认 : | E13: 价格影响确认： | L13: 支付特许权使用费 : | T13: 自报自缴 : 出口不填 | X13: 原产国/目的国/货源地未注明的项默认与提供的项相同
A14: 项号 商品编号 商品名称及规格型号 数量及单位 单价/总价/币制 原产国（地区） 最终目的国（地区） 境内货源地 征免 | AC14: 毛重(KG) | AD14: 净重(KG) | AE14: 件数
A15: 1 | B15: =E19 -> 6302539090 | E15: 纺织产品桌布 0|0|餐桌用|机织|100% 聚酯纤维 | L15: 2440 | M15: 件 | N15: =P15/L15 -> 1.55 | P15: 3782 | Q15: 美元 | S15: 中国 | U15: =$I$8 -> 美国 | X15: 深圳特区 | AC15: 997.35 | AD15: 866.81 | AE15: 61
A16: 2
A17: 申报要素
A18: 序号 | C18: 品名 | E18: 海关HS编码 | G18: 检疫附加码 | I18: 品牌 | L18: 型号 | M18: 品牌类型 | P18: 出口享惠情况 | T18: 其他申报要素
A19: 1 | B19: 1 | C19: 纺织产品桌布 | E19: 6302539090 | F19: 4202129000 | I19: 无 | L19: 无 | M19: 无 | P19: 2不确定享惠 | T19: 1:品名：纺织产品桌布;2:品牌类型：无;3:出口享惠情况：不确定享惠; ;4:表面材质及成分含量：聚酯纤维
A20: 2
A21: 3

Sheet 发票
A1: 發票
A2: INVOICE
N3: 編 號 | S3: =报关单!A8 -> EF-C26037-AVP1
N4: NO:
A5: 商 號 | E5: Amazon.com Services, Inc. | N5: 日 期 | S5: =报关单!V4 -> 46160
A6: Sold to Massrs: | N6: DATE:
O8: 成交方式： | S8: FOB SHENZHEN
A9: 標記號碼 Mark & No | E9: 貨物名稱 Description | L9: 數量 Quantity | N9: 單價 Unit price | S9: 總金額 Amount
A10: FBA19CNNVCHX | E10: =报关单!C19 -> 纺织产品桌布 | L10: =报关单!L15 -> 2440 | M10: =报关单!M15 -> 件 | N10: =报关单!N15 -> 1.55 | S10: =报关单!P15 -> 3782
A12: 0 | E12: =报关单!C20 -> 0 | L12: =报关单!L16 -> 0 | M12: =报关单!M16 -> 0 | N12: =报关单!N16 -> 0 | S12: =报关单!P16 -> 0
A13: 0 | E13: =报关单!C21 -> 0 | L13: =报关单!#REF! -> #REF! | M13: =报关单!#REF! -> #REF! | N13: =报关单!#REF! -> #REF! | S13: =报关单!#REF! -> #REF!
G14: 总数： | L14: =SUM(L10:L13) -> #REF! | N14: TOTAL: | S14: =SUM(S10:U13) -> #REF! | V14: 美元
A15: 唛头 | N15: 备注：
A16: Marks

Sheet 装箱单
G1: 装 箱 单 | O1: 日期
F2: PACKING LIST | T2: =报关单!V4 -> 46160
O3: Date：
O4: 发票编号 | T4: =报关单!A8 -> EF-C26037-AVP1
O5: Invoice No:
A6: 客户 | D6: 许昌易尚电子商务有限公司 | O6: 合同号 | T6: =报关单!A8 -> EF-C26037-AVP1
A7: To Messrs: | O7: Contract No:
A8: 船名 | I8: 由深圳至 | M8: =报关单!I8 -> 美国 | O8: 付款条件 电汇
A9: Shipped
O10: Terms of Payment:
A11: 箱号 Ctn.No. | D11: 货物名称及规格 Description | I11: 箱数： Pkg： | L11: 数量： Ge.Quantity | O11: 毛重(KG)： G.W. (KG): | T11: 净重(KG)： N.W. (KG):
A12: FBA19CNNVCHX | D12: =报关单!C19 -> 纺织产品桌布 | I12: =报关单!AE15 -> 61 | L12: =报关单!L15 -> 2440 | N12: =报关单!M15 -> 件 | O12: =报关单!AC15 -> 997.35 | T12: =报关单!AD15 -> 866.81
A16: 合计 Total | I16: =SUM(I12:K15) -> 61 | L16: =SUM(L12:M15) -> 2440 | O16: =SUM(O12:S15) -> 997.35 | T16: =SUM(T12:X15) -> 866.81
A17: 唛头
A18: Marks

Sheet 合同
A1: 合 同
A2: SALES CONTRACT
B3: 卖 方： | E3: 许昌易尚电子商务有限公司
B4: Sellers:
B5: 地 址： | E5: 7th Floor, Building 2, Xuchang Urban-Rural Integration Demonstration Zone, Furong Avenue E-Commerce Industrial Park, Xuchang City, Henan Province, China
B6: Address: | O6: 合同号码
B7: 电 话： | E7: 传 真 | O7: Contract No: | R7: =报关单!A8 -> EF-C26037-AVP1
C8: TEL: | H8: FAX: | O8: 日 期 —______
B9: 买 方： | O9: Date: | R9: =报关单!V4 -> 46160
B10: Buyers： | O10: 签约地点—_______
B11: 地 址： | O11: Signed at: 深圳
B12: Address: | O12: 成交方式：FOB
B13: 电 话 | E13: 传 真 FAX: | O13: Trade Term : FOB SHENZHEN
B14: TEL:
A15: 经买卖双方确认根据下列条款订立本合同
A16: This contract is made out by the Sellers and Buyers as per the following terms and conditions mutuilly confirmed:
A17: (1)货物名称 Name of commodity | H17: (2) 数 量 Quantity | L17: (3)单 位 Unit | O17: (4)单价 Unit Price | S17: (5) 金 额(USD) Amount
A18: =报关单!C19 -> 纺织产品桌布 | H18: =报关单!L15 -> 2440 | L18: =报关单!M15 -> 件 | O18: =报关单!N15 -> 1.55 | S18: =报关单!P15 -> 3782
A34: 数量及总值允许有 2 %的增减。 总 值(USD) 2 % more or less both in amount and quantity allowed. Total Amount:
S35: =SUM(S18:W33) -> 3782
A36: (6)合同总值（USD） | E36: =S35 -> 3782
A37: Total Value in Word:SEVEN HUNDRED AND SEVEN AND SEVENTY ONLY.
A38: (7)包装及唛头
A39: Packing and shipping Marks: (8)装运期
A40: Time of Shipment: | E40: =报关单!V4+3 -> 46163 | I40: 之前
A41: (9)装运口岸和目的地 | E41: 深圳-- | G41: =报关单!I8 -> 美国 | I41: 准许分批与转船。
A42: Loading Port & Destination:From Shenzhen-- To Hongkong with transhipment and partial ship ments allowed (10)保险：由买方按发票全部金额110%投保至 为止的 险。按中国海洋运输保险条款 Insurance:To be covered by the Buyer for 110% of full invoice value covering up to only,subject to C.I.C. (11)付款条件 电汇 Terms of Payment (12)装运标记 Shipping Marks:
A43: 买 方 | L43: 卖 方
A44: THE BUYERS | L44: THE SELLERS
A45: (香港年轻兄弟科技有限公司) | L45: (深圳市海思拓普科技有限公司)

Sheet 委托协议
A1: 代 理 报 关 委 托 书
L2: 编号： □□□□□□□□□□□
A3: 我单位现 A (A逐票、B长期)委托贵公司代理 AB 等通关事宜。 （A、填单申报 B、辅助查验 C、 垫缴税款 D、办理海关证明联 E、审批手册 F、核销手册 G、 申办减免税手续 H、其他 ）详见《委托报关协 议》。
A4: 我单位保证遵守《海关法》和国家有关法规，保证所提供的情况真实、完整、单货相符，无侵犯他 人知识产权的行为。否则，愿承担相关法律责任。
A5: 本委托书有效期自签字之日起至
L6: 委托方（盖章）：
A7: 法定代表人或其授权签署《代理报关委托书》的人（签字）
P8: =报关单!V4-1 -> 46159
A9: 委 托 报 关 协 议
A10: 为明确委托报关具体事项和各自责任，双方经平等协商签定协议如下：
A11: 委托方 | D11: 许昌易尚电子商务有限公司 | L11: 被委托方
A12: 主要货物名称 | D12: 聚酯纤维桌布 | L12: *报关单编码
A13: HS编码 | D13: 6302539090 | L13: 收到单证日期 | N13: =报关单!V4 -> 46160
A14: 货物总价 | D14: 美元 | F14: =SUM(报关单!P15:P16) -> 3782 | L14: 收到单证情况 | N14: 合同□√ | T14: 发票□√
A15: 进出口日期 | D15: =报关单!V4+3 -> 46163 | N15: 装箱清单□√ | T15: 提（运）单□
A16: 提单号 | N16: 加工贸易手册□ | T16: 许可证件□
A17: 贸易方式 | D17: 一般贸易 | N17: 其他
A18: 原产地/货源地 | D18: 中国 | L18: 报关收费 | N18: 人民币： 元
A19: 其他要求： | L19: 承诺说明：
A20: 背面所列通用条款是本协议不可分割的一部分，对本协议的签署构 成了对背面通用条款的同意。 | L20: 背面所列通用条款是本协议不可分割的一部分，对本协议的签署构 成了对背面通用条款的同意。
A21: 委托方业务签章： | L21: 被委托方业务签章：
A22: 经办人签章： 联系电话： | D22: =报关单!V4 -> 46160 | L22: 经办报关员签章： 联系电话： | N22: =报关单!V4+1 -> 46161
A23: （白联：海关留存、黄联：被委托方留存、红联：委托方留存） | S23: 中国报关协会监制
